snapsheets/__init__.py
snapsheets/book.py
snapsheets/downloader.py
snapsheets/sheet.py
snapsheets/v0/__init__.py
snapsheets/v0/core.py
snapsheets/v1.py
snapsheets-1.1.1.dist-info/LICENSE
snapsheets-1.1.1.dist-info/METADATA
snapsheets-1.1.1.dist-info/WHEEL
snapsheets-1.1.1.dist-info/entry_points.txt
snapsheets-1.1.1.dist-info/RECORD
