Metadata-Version: 2.1
Name: snapsheets
Version: 1.1.1
Summary: Quick and Easy Downloader for Public Google Spreadsheets
Home-page: https://qumasan.gitlab.io/snapsheets/
License: MIT
Keywords: wget,googlesheet
Author: shotakaha
Author-email: shotakaha+py@gmail.com
Requires-Python: >=3.10,<4.0
Classifier: Development Status :: 4 - Beta
Classifier: Environment :: Console
Classifier: Intended Audience :: Developers
Classifier: Intended Audience :: Science/Research
Classifier: License :: OSI Approved :: MIT License
Classifier: Natural Language :: Japanese
Classifier: Programming Language :: Python :: 3
Classifier: Programming Language :: Python :: 3.10
Classifier: Programming Language :: Python :: 3.11
Classifier: Programming Language :: Python :: 3.12
Requires-Dist: Deprecated (>=1.2.12,<2.0.0)
Requires-Dist: PyYAML (>=6.0,<7.0)
Requires-Dist: httpx (>=0.27.2,<0.28.0)
Requires-Dist: loguru (>=0.7.2,<0.8.0)
Requires-Dist: requests (>=2.32.3,<3.0.0)
Requires-Dist: tomli (>=2.0.1,<3.0.0)
Requires-Dist: typer (>=0.12.5,<0.13.0)
Project-URL: Repository, https://gitlab.com/qumasan/snapsheets/
